transform_field/__init__.py
transform_field/errors.py
transform_field/timings.py
transform_field/transform.py
transform_field/utils.py
pipelinewise_transform_field-2.3.0.dist-info/LICENSE
pipelinewise_transform_field-2.3.0.dist-info/METADATA
pipelinewise_transform_field-2.3.0.dist-info/WHEEL
pipelinewise_transform_field-2.3.0.dist-info/entry_points.txt
pipelinewise_transform_field-2.3.0.dist-info/top_level.txt
pipelinewise_transform_field-2.3.0.dist-info/RECORD
