Metadata-Version: 2.1
Name: pipelinewise-transform-field
Version: 2.3.0
Summary: Singer.io simple field transformer between taps and targets - PipelineWise compatible
Home-page: https://github.com/transferwise/pipelinewise-transform-field
Author: Wise
License: UNKNOWN
Platform: UNKNOWN
Classifier: License :: OSI Approved :: Apache Software License
Classifier: Environment :: Console
Classifier: Programming Language :: Python :: 3 :: Only
Classifier: Programming Language :: Python :: 3.6
Classifier: Programming Language :: Python :: 3.7
Classifier: Programming Language :: Python :: 3.8
License-File: LICENSE
Requires-Dist: pipelinewise-singer-python (==1.*)
Requires-Dist: dpath (==2.0.*)
Provides-Extra: test
Requires-Dist: pytest (==6.2.*) ; extra == 'test'
Requires-Dist: pytest-cov (==3.0.*) ; extra == 'test'
Requires-Dist: pylint (==2.12.*) ; extra == 'test'
